LICENSE
MANIFEST.in
README.rst
requirements.txt
setup.cfg
setup.py
kiss/__init__.py
kiss/classes.py
kiss/constants.py
kiss/exceptions.py
kiss/util.py
kiss.egg-info/PKG-INFO
kiss.egg-info/SOURCES.txt
kiss.egg-info/dependency_links.txt
kiss.egg-info/not-zip-safe
kiss.egg-info/pbr.json
kiss.egg-info/requires.txt
kiss.egg-info/top_level.txt