Metadata-Version: 1.1
Name: kiss
Version: 6.0.0
Summary: Python KISS Module.
Home-page: https://github.com/ampledata/kiss
Author: Greg Albrecht
Author-email: oss@undef.net
License: Copyright 2016 Orion Labs, Inc. and Contributors
